rundeck_resources/__init__.py
rundeck_resources/cache.py
rundeck_resources/chef_importer.py
rundeck_resources/cli.py
rundeck_resources/common.py
rundeck_resources/config.py
rundeck_resources/errors.py
rundeck_resources/foreman_importer.py
rundeck_resources/interfaces.py
rundeck_resources/logger.py
rundeck_resources/plugins.py
rundeck_resources/yaml_exporter.py
rundeck_resources-0.3.9.dist-info/METADATA
rundeck_resources-0.3.9.dist-info/RECORD
rundeck_resources-0.3.9.dist-info/WHEEL
rundeck_resources-0.3.9.dist-info/entry_points.txt
rundeck_resources-0.3.9.dist-info/top_level.txt
