Metadata-Version: 2.1
Name: rundeck-resources
Version: 0.3.9
Summary: Rundeck Resources Generator
Home-page: https://gitlab.com/elazkani/rundeck-resources
Author: Elia El Lazkani
Author-email: eliaellazkani@gmail.com
License: BSD
Platform: UNKNOWN
Classifier: Development Status :: 4 - Beta
Classifier: License :: OSI Approved :: BSD License
Classifier: Operating System :: POSIX :: Linux
Classifier: Operating System :: MacOS :: MacOS X
Classifier: Programming Language :: Python
Classifier: Programming Language :: Python :: 3.5
Classifier: Programming Language :: Python :: 3.6
Classifier: Programming Language :: Python :: 3.7
Classifier: Environment :: Console
Classifier: Intended Audience :: Information Technology
Classifier: Intended Audience :: System Administrators
Requires-Python: >=python3.5
Requires-Dist: pychef
Requires-Dist: PyYAML
